miceapi_async.py
miceapi.cpython-37m-x86_64-linux-gnu.so
miceapi-1.0.3.dev6.dist-info/WHEEL
miceapi-1.0.3.dev6.dist-info/top_level.txt
miceapi-1.0.3.dev6.dist-info/RECORD
miceapi-1.0.3.dev6.dist-info/LICENSE.txt
miceapi-1.0.3.dev6.dist-info/METADATA
