Metadata-Version: 2.1
Name: miceapi
Version: 1.0.3.dev6
Summary: An API for managing multiple simultaneous mice input on Linux
Home-page: https://github.com/m3101/miceapi
Author: Amélia O. F. da S.
Author-email: a.mellifluous.one@gmail.com
License: MIT
Keywords: mouse mice touchpad multiple simultaneous
Platform: UNKNOWN
Classifier: Development Status :: 2 - Pre-Alpha
Classifier: Programming Language :: C
Classifier: License :: OSI Approved :: MIT License
Classifier: Operating System :: POSIX :: Linux
Classifier: Topic :: Scientific/Engineering :: Interface Engine/Protocol Translator
Classifier: Topic :: Software Development :: User Interfaces
Requires-Python: >=3
